{
  "$schema": "https://dl.viam.dev/module.schema.json",
  "module_id": "viam:orange-pi",
  "visibility": "public",
  "url": "https://github.com/viam-modules/orange-pi",
  "description": "Go module for orange-pi orangepi board, compatible with Viam",
  "models": [
    {
      "api": "rdk:component:board",
      "model": "viam:orange-pi:orangepi"
    }
  ],
  "build": {
    "build": "make module",
    "path": "bin/module.tar.gz",
    "arch" : ["linux/arm64"]
  },
  "entrypoint": "bin/orange-pi"
}